MANIFEST.in
README.md
setup.cfg
setup.py
versioneer.py
layout_expert/__init__.py
layout_expert/_version.py
layout_expert/layout_tool.py
layout_expert/builtins/__init__.py
layout_expert/builtins/functions.py
layout_expert/builtins/functions_test.py
layout_expert/builtins/gcc_constants.py
layout_expert/builtins/types.py
layout_expert/c_ast/__init__.py
layout_expert/c_ast/c_ast.py
layout_expert/c_ast/pre_ast.py
layout_expert/c_ast/visitor_mixin.py
layout_expert/c_ast/visitor_mixin_test.py
layout_expert/common/__init__.py
layout_expert/common/data_container.py
layout_expert/common/data_container_test.py
layout_expert/common/key_aware_defaultdict.py
layout_expert/config_parser/__init__.py
layout_expert/config_parser/config_parser.py
layout_expert/config_parser/config_parser_test.py
layout_expert/layout/__init__.py
layout_expert/layout/layout.py
layout_expert/layout/layout_to_vtype_converter.py
layout_expert/layout/layout_to_vtype_converter_test.py
layout_expert/lib/__init__.py
layout_expert/lib/layout_manager.py
layout_expert/lib/parsers.py
layout_expert/lib/type_manager.py
layout_expert/parsers/__init__.py
layout_expert/parsers/c_parser.py
layout_expert/parsers/expression_parser.py
layout_expert/parsers/expression_parser_test.py
layout_expert/parsers/parser_test.py
layout_expert/parsers/trimming_parser.py
layout_expert/parsers/trimming_parser_test.py
layout_expert/parsers/util.py
layout_expert/preprocessing_loader/__init__.py
layout_expert/preprocessing_loader/preprocessing_loader.py
layout_expert/preprocessing_loader/preprocessing_loader_test.py
layout_expert/preprocessing_parser/__init__.py
layout_expert/preprocessing_parser/preprocessing_parser.py
layout_expert/preprocessing_parser/preprocessing_parser_test.py
layout_expert/preprocessing_visitors/__init__.py
layout_expert/preprocessing_visitors/include_collecting_visitor.py
layout_expert/preprocessing_visitors/include_collecting_visitor_test.py
layout_expert/preprocessing_visitors/include_linking_visitor.py
rekall_layout_expert.egg-info/PKG-INFO
rekall_layout_expert.egg-info/SOURCES.txt
rekall_layout_expert.egg-info/dependency_links.txt
rekall_layout_expert.egg-info/entry_points.txt
rekall_layout_expert.egg-info/requires.txt
rekall_layout_expert.egg-info/top_level.txt