Metadata-Version: 1.1
Name: rekall-layout-expert
Version: 1.5.0.post4
Summary: Rekall Layout Expert
Home-page: https://www.rekall-forensic.com/
Author: The Rekall team
Author-email: rekall-discuss@googlegroups.com
License: Apache
Platform: UNKNOWN
Classifier: Development Status :: 4 - Beta
Classifier: Environment :: Console
Classifier: Operating System :: OS Independent
Classifier: Programming Language :: Python
